embark/__init__.py
embark/foo.py
embark-0.0.3.dist-info/LICENSE
embark-0.0.3.dist-info/METADATA
embark-0.0.3.dist-info/WHEEL
embark-0.0.3.dist-info/RECORD
