Metadata-Version: 2.1
Name: embark
Version: 0.0.3
Summary: embark anything.
Home-page: https://github.com/nlile/embark
Author: nlile
Author-email: n@synthlabs.ai
Requires-Python: >=3.8,<4.0
Classifier: Programming Language :: Python :: 3
Classifier: Programming Language :: Python :: 3.8
Classifier: Programming Language :: Python :: 3.9
Classifier: Programming Language :: Python :: 3.10
Classifier: Programming Language :: Python :: 3.11
Classifier: Programming Language :: Python :: 3.12
Classifier: Programming Language :: Python :: 3.13
Requires-Dist: pydantic-settings (>=2.7.1,<3.0.0)
Project-URL: Documentation, https://nlile.github.io/embark/
Project-URL: Repository, https://github.com/nlile/embark
